LONMF/model.py
LONMF/utils.py
scMO_LONMF-0.0.1.dist-info/LICENSE
scMO_LONMF-0.0.1.dist-info/METADATA
scMO_LONMF-0.0.1.dist-info/WHEEL
scMO_LONMF-0.0.1.dist-info/top_level.txt
scMO_LONMF-0.0.1.dist-info/RECORD
