Metadata-Version: 2.1
Name: scMO-LONMF
Version: 0.0.1
Summary: A non-negative matrix factorization model based on graph Laplacian and optimal transmission for Paired single-cell multi-omics data integration.
Home-page: https://github.com/NMD-CompBio/LONMF
Author: Mengdi Nan
Author-email: 2139698547@qq.com
Classifier: Programming Language :: Python :: 3
Classifier: License :: OSI Approved :: MIT License
Classifier: Operating System :: OS Independent
Requires-Python: >=3.8
License-File: LICENSE
